nmdc_submission_schema/__init__.py
nmdc_submission_schema/_version.py
nmdc_submission_schema/datamodel/__init__.py
nmdc_submission_schema/datamodel/nmdc_submission_schema.py
nmdc_submission_schema/project/json/nmdc_submission_schema.json
nmdc_submission_schema/project/jsonschema/nmdc_submission_schema.schema.json
nmdc_submission_schema/project/thirdparty/GoldEcosystemTree.json
nmdc_submission_schema/schema/.gitkeep
nmdc_submission_schema/schema/nmdc_submission_schema.yaml
nmdc_submission_schema/schema/nmdc_submission_schema_base.yaml
nmdc_submission_schema-11.15.0.dist-info/METADATA
nmdc_submission_schema-11.15.0.dist-info/WHEEL
nmdc_submission_schema-11.15.0.dist-info/licenses/LICENSE
nmdc_submission_schema-11.15.0.dist-info/RECORD
