Metadata-Version: 2.4
Name: nmdc_submission_schema
Version: 11.15.0
Summary: The NMDC submission schema
License: MIT
License-File: LICENSE
Author: Mark Andrew Miller
Author-email: mam@lbl.gov
Requires-Python: >=3.10,<4.0
Classifier: License :: OSI Approved :: MIT License
Classifier: Programming Language :: Python :: 3
Classifier: Programming Language :: Python :: 3.10
Classifier: Programming Language :: Python :: 3.11
Classifier: Programming Language :: Python :: 3.12
Classifier: Programming Language :: Python :: 3.13
Classifier: Programming Language :: Python :: 3.14
Provides-Extra: docs
Requires-Dist: linkml-runtime (>=1.6.2,<2.0.0)
Requires-Dist: rdflib (>=6.2.0,<7.0.0)
